mergecli/__init__.py
mergecli/__main__.py
mergecli/mergecli.py
shapeshiftercli/__init__.py
shapeshiftercli/__main__.py
shapeshiftercli/shapeshiftercli.py
shapeshifter_cli-1.0.0.dist-info/LICENSE
shapeshifter_cli-1.0.0.dist-info/METADATA
shapeshifter_cli-1.0.0.dist-info/WHEEL
shapeshifter_cli-1.0.0.dist-info/entry_points.txt
shapeshifter_cli-1.0.0.dist-info/top_level.txt
shapeshifter_cli-1.0.0.dist-info/RECORD
